pixeljump/__init__.py
pixeljump/animations.py
pixeljump/assets/Cirrocumulus_cloud_3.png
pixeljump/assets/Cirrus_cloud_2.png
pixeljump/assets/Cumulonimbus_cloud_2.png
pixeljump/assets/KNIGHT.png
pixeljump/assets/Regular_cloud_2.png
pixeljump/assets/SECONDMODEL.png
pixeljump/assets/TILES/0.png
pixeljump/assets/TILES/1.png
pixeljump/assets/TILES/2.png
pixeljump/assets/TILES/3.png
pixeljump/assets/TILES/4.png
pixeljump/assets/TILES/5.png
pixeljump/assets/TILES/6.png
pixeljump/assets/TILES/7.png
pixeljump/assets/TILES/8.png
pixeljump/assets/TILES/9.png
pixeljump/assets/TILES2/1.png
pixeljump/assets/TILES2/2.png
pixeljump/assets/TILES2/3.png
pixeljump/assets/TILES2/4.png
pixeljump/assets/TILES2/5.png
pixeljump/assets/TILES2/6.png
pixeljump/assets/TILES2/7.png
pixeljump/assets/TILES2/8.png
pixeljump/assets/TILES2/9.png
pixeljump/assets/TILES3/0.png
pixeljump/assets/TILES3/1.png
pixeljump/assets/TILES3/2.png
pixeljump/assets/TILES3/3.png
pixeljump/assets/TILES3/4.png
pixeljump/assets/TILES3/5.png
pixeljump/assets/TILES3/6.png
pixeljump/assets/TILES3/7.png
pixeljump/assets/TILES3/8.png
pixeljump/assets/TILES3/9.png
pixeljump/assets/alien1.png
pixeljump/assets/alien1_flying/alien1_flying_0.png
pixeljump/assets/alien1_flying/alien1_flying_1.png
pixeljump/assets/alien1_flying/alien1_flying_2.png
pixeljump/assets/alien1_flying/alien1_flying_3.png
pixeljump/assets/alien1_flying/alien1_flying_4.png
pixeljump/assets/alien1_flying/alien1_flying_5.png
pixeljump/assets/alien1_flying/alien1_flying_6.png
pixeljump/assets/alien1_flying/alien1_flying_7.png
pixeljump/assets/alien2.png
pixeljump/assets/alien2_idle/alien2_idle_0.png
pixeljump/assets/alien2_idle/alien2_idle_1.png
pixeljump/assets/alien2_idle/alien2_idle_2.png
pixeljump/assets/alien2_idle/alien2_idle_3.png
pixeljump/assets/alien2_walking/alien2_walking_0.png
pixeljump/assets/alien2_walking/alien2_walking_1.png
pixeljump/assets/alien2_walking/alien2_walking_2.png
pixeljump/assets/alien2_walking/alien2_walking_3.png
pixeljump-1.0.0.dist-info/entry_points.txt
pixeljump-1.0.0.dist-info/WHEEL
pixeljump-1.0.0.dist-info/METADATA
pixeljump-1.0.0.dist-info/RECORD
