Metadata-Version: 2.1
Name: pixeljump
Version: 1.0.0
Summary: NUS Orbital 21/22 Team PixelJump
Home-page: https://github.com/WilsonOh/Orbital21-22-PixelJump-5215
License: MIT
Author: Wilson Oh
Author-email: e0773510@u.nus.edu
Requires-Python: >=3.10,<3.11
Classifier: License :: OSI Approved :: MIT License
Classifier: Programming Language :: Python :: 3
Classifier: Programming Language :: Python :: 3.10
Requires-Dist: lizard (>=1.17.10,<2.0.0)
Requires-Dist: pygame (>=2.1.2,<3.0.0)
Requires-Dist: pygame-widgets (>=1.0.0,<2.0.0)
Project-URL: Repository, https://github.com/WilsonOh/Orbital21-22-PixelJump-5215
